[{"id":0,"question":"1+2","choices":[2,3,4],"rightAnswer":3,"qOperator":"+","difficultyLevel":1,"isPassed":false,"isCorrect":false},{"id":1,"question":"2+0","choices":[1,2,3],"rightAnswer":2,"qOperator":"+","difficultyLevel":1,"isPassed":false,"isCorrect":false},{"id":2,"question":"2+9","choices":[10,11,12],"rightAnswer":11,"qOperator":"+","difficultyLevel":1,"isPassed":false,"isCorrect":false},{"id":3,"question":"9+4","choices":[12,13,14],"rightAnswer":13,"qOperator":"+","difficultyLevel":1,"isPassed":false,"isCorrect":false},{"id":4,"question":"4+5","choices":[8,9,10],"rightAnswer":9,"qOperator":"+","difficultyLevel":1,"isPassed":false,"isCorrect":false},{"id":5,"question":"0+3","choices":[2,3,4],"rightAnswer":3,"qOperator":"+","difficultyLevel":1,"isPassed":false,"isCorrect":false},{"id":6,"question":"8+0","choices":[7,8,9],"rightAnswer":8,"qOperator":"+","difficultyLevel":1,"isPassed":false,"isCorrect":false},{"id":7,"question":"9+5","choices":[13,14,15],"rightAnswer":14,"qOperator":"+","difficultyLevel":1,"isPassed":false,"isCorrect":false},{"id":8,"question":"6+0","choices":[5,6,7],"rightAnswer":6,"qOperator":"+","difficultyLevel":1,"isPassed":false,"isCorrect":false},{"id":9,"question":"3+1","choices":[3,4,5],"rightAnswer":4,"qOperator":"+","difficultyLevel":1,"isPassed":false,"isCorrect":false},{"id":10,"question":"2+9","choices":[10,11,12],"rightAnswer":11,"qOperator":"+","difficultyLevel":1,"isPassed":false,"isCorrect":false},{"id":11,"question":"5+2","choices":[6,7,8],"rightAnswer":7,"qOperator":"+","difficultyLevel":1,"isPassed":false,"isCorrect":false},{"id":12,"question":"8+1","choices":[8,9,10],"rightAnswer":9,"qOperator":"+","difficultyLevel":1,"isPassed":false,"isCorrect":false},{"id":13,"question":"9+8","choices":[16,17,18],"rightAnswer":17,"qOperator":"+","difficultyLevel":1,"isPassed":false,"isCorrect":false},{"id":14,"question":"1+2","choices":[2,3,4],"rightAnswer":3,"qOperator":"+","difficultyLevel":1,"isPassed":false,"isCorrect":false},{"id":15,"question":"9+3","choices":[11,12,13],"rightAnswer":12,"qOperator":"+","difficultyLevel":1,"isPassed":false,"isCorrect":false},{"id":16,"question":"4+2","choices":[5,6,7],"rightAnswer":6,"qOperator":"+","difficultyLevel":1,"isPassed":false,"isCorrect":false},{"id":17,"question":"4+6","choices":[9,10,11],"rightAnswer":10,"qOperator":"+","difficultyLevel":1,"isPassed":false,"isCorrect":false},{"id":18,"question":"6+9","choices":[14,15,16],"rightAnswer":15,"qOperator":"+","difficultyLevel":1,"isPassed":false,"isCorrect":false},{"id":19,"question":"9+5","choices":[13,14,15],"rightAnswer":14,"qOperator":"+","difficultyLevel":1,"isPassed":false,"isCorrect":false},{"id":20,"question":"14+9","choices":[22,23,24],"rightAnswer":23,"qOperator":"+","difficultyLevel":2,"isPassed":false,"isCorrect":false},{"id":21,"question":"86+5","choices":[90,91,92],"rightAnswer":91,"qOperator":"+","difficultyLevel":2,"isPassed":false,"isCorrect":false},{"id":22,"question":"90+9","choices":[98,99,100],"rightAnswer":99,"qOperator":"+","difficultyLevel":2,"isPassed":false,"isCorrect":false},{"id":23,"question":"58+9","choices":[66,67,68],"rightAnswer":67,"qOperator":"+","difficultyLevel":2,"isPassed":false,"isCorrect":false},{"id":24,"question":"58+5","choices":[62,63,64],"rightAnswer":63,"qOperator":"+","difficultyLevel":2,"isPassed":false,"isCorrect":false},{"id":25,"question":"92+8","choices":[99,100,101],"rightAnswer":100,"qOperator":"+","difficultyLevel":2,"isPassed":false,"isCorrect":false},{"id":26,"question":"16+3","choices":[18,19,20],"rightAnswer":19,"qOperator":"+","difficultyLevel":2,"isPassed":false,"isCorrect":false},{"id":27,"question":"26+1","choices":[26,27,28],"rightAnswer":27,"qOperator":"+","difficultyLevel":2,"isPassed":false,"isCorrect":false},{"id":28,"question":"82+7","choices":[88,89,90],"rightAnswer":89,"qOperator":"+","difficultyLevel":2,"isPassed":false,"isCorrect":false},{"id":29,"question":"95+4","choices":[98,99,100],"rightAnswer":99,"qOperator":"+","difficultyLevel":2,"isPassed":false,"isCorrect":false},{"id":30,"question":"42+1","choices":[42,43,44],"rightAnswer":43,"qOperator":"+","difficultyLevel":2,"isPassed":false,"isCorrect":false},{"id":31,"question":"30+1","choices":[30,31,32],"rightAnswer":31,"qOperator":"+","difficultyLevel":2,"isPassed":false,"isCorrect":false},{"id":32,"question":"48+2","choices":[49,50,51],"rightAnswer":50,"qOperator":"+","difficultyLevel":2,"isPassed":false,"isCorrect":false},{"id":33,"question":"71+4","choices":[74,75,76],"rightAnswer":75,"qOperator":"+","difficultyLevel":2,"isPassed":false,"isCorrect":false},{"id":34,"question":"38+2","choices":[39,40,41],"rightAnswer":40,"qOperator":"+","difficultyLevel":2,"isPassed":false,"isCorrect":false},{"id":35,"question":"23+3","choices":[25,26,27],"rightAnswer":26,"qOperator":"+","difficultyLevel":2,"isPassed":false,"isCorrect":false},{"id":36,"question":"29+7","choices":[35,36,37],"rightAnswer":36,"qOperator":"+","difficultyLevel":2,"isPassed":false,"isCorrect":false},{"id":37,"question":"52+2","choices":[53,54,55],"rightAnswer":54,"qOperator":"+","difficultyLevel":2,"isPassed":false,"isCorrect":false},{"id":38,"question":"82+7","choices":[88,89,90],"rightAnswer":89,"qOperator":"+","difficultyLevel":2,"isPassed":false,"isCorrect":false},{"id":39,"question":"20+7","choices":[26,27,28],"rightAnswer":27,"qOperator":"+","difficultyLevel":2,"isPassed":false,"isCorrect":false},{"id":40,"question":"23+13","choices":[35,36,37],"rightAnswer":36,"qOperator":"+","difficultyLevel":3,"isPassed":false,"isCorrect":false},{"id":41,"question":"75+48","choices":[122,123,124],"rightAnswer":123,"qOperator":"+","difficultyLevel":3,"isPassed":false,"isCorrect":false},{"id":42,"question":"85+43","choices":[127,128,129],"rightAnswer":128,"qOperator":"+","difficultyLevel":3,"isPassed":false,"isCorrect":false},{"id":43,"question":"17+69","choices":[85,86,87],"rightAnswer":86,"qOperator":"+","difficultyLevel":3,"isPassed":false,"isCorrect":false},{"id":44,"question":"23+97","choices":[119,120,121],"rightAnswer":120,"qOperator":"+","difficultyLevel":3,"isPassed":false,"isCorrect":false},{"id":45,"question":"79+62","choices":[140,141,142],"rightAnswer":141,"qOperator":"+","difficultyLevel":3,"isPassed":false,"isCorrect":false},{"id":46,"question":"85+58","choices":[142,143,144],"rightAnswer":143,"qOperator":"+","difficultyLevel":3,"isPassed":false,"isCorrect":false},{"id":47,"question":"10+10","choices":[19,20,21],"rightAnswer":20,"qOperator":"+","difficultyLevel":3,"isPassed":false,"isCorrect":false},{"id":48,"question":"64+84","choices":[147,148,149],"rightAnswer":148,"qOperator":"+","difficultyLevel":3,"isPassed":false,"isCorrect":false},{"id":49,"question":"28+61","choices":[88,89,90],"rightAnswer":89,"qOperator":"+","difficultyLevel":3,"isPassed":false,"isCorrect":false},{"id":50,"question":"69+14","choices":[82,83,84],"rightAnswer":83,"qOperator":"+","difficultyLevel":3,"isPassed":false,"isCorrect":false},{"id":51,"question":"45+87","choices":[131,132,133],"rightAnswer":132,"qOperator":"+","difficultyLevel":3,"isPassed":false,"isCorrect":false},{"id":52,"question":"31+90","choices":[120,121,122],"rightAnswer":121,"qOperator":"+","difficultyLevel":3,"isPassed":false,"isCorrect":false},{"id":53,"question":"47+20","choices":[66,67,68],"rightAnswer":67,"qOperator":"+","difficultyLevel":3,"isPassed":false,"isCorrect":false},{"id":54,"question":"60+16","choices":[75,76,77],"rightAnswer":76,"qOperator":"+","difficultyLevel":3,"isPassed":false,"isCorrect":false},{"id":55,"question":"23+80","choices":[102,103,104],"rightAnswer":103,"qOperator":"+","difficultyLevel":3,"isPassed":false,"isCorrect":false},{"id":56,"question":"85+48","choices":[132,133,134],"rightAnswer":133,"qOperator":"+","difficultyLevel":3,"isPassed":false,"isCorrect":false},{"id":57,"question":"67+73","choices":[139,140,141],"rightAnswer":140,"qOperator":"+","difficultyLevel":3,"isPassed":false,"isCorrect":false},{"id":58,"question":"12+65","choices":[76,77,78],"rightAnswer":77,"qOperator":"+","difficultyLevel":3,"isPassed":false,"isCorrect":false},{"id":59,"question":"10+39","choices":[48,49,50],"rightAnswer":49,"qOperator":"+","difficultyLevel":3,"isPassed":false,"isCorrect":false},{"id":60,"question":"744+63","choices":[806,807,808],"rightAnswer":807,"qOperator":"+","difficultyLevel":4,"isPassed":false,"isCorrect":false},{"id":61,"question":"164+27","choices":[190,191,192],"rightAnswer":191,"qOperator":"+","difficultyLevel":4,"isPassed":false,"isCorrect":false},{"id":62,"question":"625+68","choices":[692,693,694],"rightAnswer":693,"qOperator":"+","difficultyLevel":4,"isPassed":false,"isCorrect":false},{"id":63,"question":"936+15","choices":[950,951,952],"rightAnswer":951,"qOperator":"+","difficultyLevel":4,"isPassed":false,"isCorrect":false},{"id":64,"question":"373+57","choices":[429,430,431],"rightAnswer":430,"qOperator":"+","difficultyLevel":4,"isPassed":false,"isCorrect":false},{"id":65,"question":"402+27","choices":[428,429,430],"rightAnswer":429,"qOperator":"+","difficultyLevel":4,"isPassed":false,"isCorrect":false},{"id":66,"question":"686+84","choices":[769,770,771],"rightAnswer":770,"qOperator":"+","difficultyLevel":4,"isPassed":false,"isCorrect":false},{"id":67,"question":"621+90","choices":[710,711,712],"rightAnswer":711,"qOperator":"+","difficultyLevel":4,"isPassed":false,"isCorrect":false},{"id":68,"question":"496+55","choices":[550,551,552],"rightAnswer":551,"qOperator":"+","difficultyLevel":4,"isPassed":false,"isCorrect":false},{"id":69,"question":"243+77","choices":[319,320,321],"rightAnswer":320,"qOperator":"+","difficultyLevel":4,"isPassed":false,"isCorrect":false},{"id":70,"question":"337+88","choices":[424,425,426],"rightAnswer":425,"qOperator":"+","difficultyLevel":4,"isPassed":false,"isCorrect":false},{"id":71,"question":"554+54","choices":[607,608,609],"rightAnswer":608,"qOperator":"+","difficultyLevel":4,"isPassed":false,"isCorrect":false},{"id":72,"question":"784+17","choices":[800,801,802],"rightAnswer":801,"qOperator":"+","difficultyLevel":4,"isPassed":false,"isCorrect":false},{"id":73,"question":"375+98","choices":[472,473,474],"rightAnswer":473,"qOperator":"+","difficultyLevel":4,"isPassed":false,"isCorrect":false},{"id":74,"question":"152+72","choices":[223,224,225],"rightAnswer":224,"qOperator":"+","difficultyLevel":4,"isPassed":false,"isCorrect":false},{"id":75,"question":"532+84","choices":[615,616,617],"rightAnswer":616,"qOperator":"+","difficultyLevel":4,"isPassed":false,"isCorrect":false},{"id":76,"question":"393+18","choices":[410,411,412],"rightAnswer":411,"qOperator":"+","difficultyLevel":4,"isPassed":false,"isCorrect":false},{"id":77,"question":"536+37","choices":[572,573,574],"rightAnswer":573,"qOperator":"+","difficultyLevel":4,"isPassed":false,"isCorrect":false},{"id":78,"question":"304+49","choices":[352,353,354],"rightAnswer":353,"qOperator":"+","difficultyLevel":4,"isPassed":false,"isCorrect":false},{"id":79,"question":"213+92","choices":[304,305,306],"rightAnswer":305,"qOperator":"+","difficultyLevel":4,"isPassed":false,"isCorrect":false},{"id":80,"question":"327+514","choices":[840,841,842],"rightAnswer":841,"qOperator":"+","difficultyLevel":5,"isPassed":false,"isCorrect":false},{"id":81,"question":"133+254","choices":[386,387,388],"rightAnswer":387,"qOperator":"+","difficultyLevel":5,"isPassed":false,"isCorrect":false},{"id":82,"question":"391+898","choices":[1288,1289,1290],"rightAnswer":1289,"qOperator":"+","difficultyLevel":5,"isPassed":false,"isCorrect":false},{"id":83,"question":"594+102","choices":[695,696,697],"rightAnswer":696,"qOperator":"+","difficultyLevel":5,"isPassed":false,"isCorrect":false},{"id":84,"question":"388+103","choices":[490,491,492],"rightAnswer":491,"qOperator":"+","difficultyLevel":5,"isPassed":false,"isCorrect":false},{"id":85,"question":"662+944","choices":[1605,1606,1607],"rightAnswer":1606,"qOperator":"+","difficultyLevel":5,"isPassed":false,"isCorrect":false},{"id":86,"question":"950+972","choices":[1921,1922,1923],"rightAnswer":1922,"qOperator":"+","difficultyLevel":5,"isPassed":false,"isCorrect":false},{"id":87,"question":"157+469","choices":[625,626,627],"rightAnswer":626,"qOperator":"+","difficultyLevel":5,"isPassed":false,"isCorrect":false},{"id":88,"question":"218+151","choices":[368,369,370],"rightAnswer":369,"qOperator":"+","difficultyLevel":5,"isPassed":false,"isCorrect":false},{"id":89,"question":"169+996","choices":[1164,1165,1166],"rightAnswer":1165,"qOperator":"+","difficultyLevel":5,"isPassed":false,"isCorrect":false},{"id":90,"question":"315+965","choices":[1279,1280,1281],"rightAnswer":1280,"qOperator":"+","difficultyLevel":5,"isPassed":false,"isCorrect":false},{"id":91,"question":"118+112","choices":[229,230,231],"rightAnswer":230,"qOperator":"+","difficultyLevel":5,"isPassed":false,"isCorrect":false},{"id":92,"question":"393+762","choices":[1154,1155,1156],"rightAnswer":1155,"qOperator":"+","difficultyLevel":5,"isPassed":false,"isCorrect":false},{"id":93,"question":"774+839","choices":[1612,1613,1614],"rightAnswer":1613,"qOperator":"+","difficultyLevel":5,"isPassed":false,"isCorrect":false},{"id":94,"question":"600+786","choices":[1385,1386,1387],"rightAnswer":1386,"qOperator":"+","difficultyLevel":5,"isPassed":false,"isCorrect":false},{"id":95,"question":"699+349","choices":[1047,1048,1049],"rightAnswer":1048,"qOperator":"+","difficultyLevel":5,"isPassed":false,"isCorrect":false},{"id":96,"question":"385+290","choices":[674,675,676],"rightAnswer":675,"qOperator":"+","difficultyLevel":5,"isPassed":false,"isCorrect":false},{"id":97,"question":"365+675","choices":[1039,1040,1041],"rightAnswer":1040,"qOperator":"+","difficultyLevel":5,"isPassed":false,"isCorrect":false},{"id":98,"question":"894+957","choices":[1850,1851,1852],"rightAnswer":1851,"qOperator":"+","difficultyLevel":5,"isPassed":false,"isCorrect":false},{"id":99,"question":"105+437","choices":[541,542,543],"rightAnswer":542,"qOperator":"+","difficultyLevel":5,"isPassed":false,"isCorrect":false}]